{
    "name": "Sulfuric Acid",
    "icon": "butcher:sulfuricacid",
    "category": "butcher:items",
    "read_by_default": true,
    "sortnum": 8,
    "pages": [
        {
            "type": "patchouli:spotlight",
            "item": "butcher:sulfuricacid",
            "link_recipe": true,
            "title" : "Sulfuric Acid",
            "text": "Acid is used to disolve a corpses flesh and organs to obtain their skeletal remains to be used as decoration. To use acid on corpses simply right click with a bottle of acid onto a corpse hanging or not and over time the skin will sizzle off leaving the skeletal remains."
        }
    ]
}
